pywe_wxa/__init__.py
pywe_wxa-1.0.1.dist-info/METADATA
pywe_wxa-1.0.1.dist-info/RECORD
pywe_wxa-1.0.1.dist-info/WHEEL
pywe_wxa-1.0.1.dist-info/top_level.txt
